balance_rxns/__init__.py
balance_rxns/core.py
balance_rxns/py.typed
balance_rxns-0.1.0.dist-info/METADATA
balance_rxns-0.1.0.dist-info/WHEEL
balance_rxns-0.1.0.dist-info/licenses/LICENSE
balance_rxns-0.1.0.dist-info/RECORD
