Metadata-Version: 2.4
Name: balance-rxns
Version: 0.1.0
Summary: A Python package for balancing chemical equations and finding possible reactions
Project-URL: Homepage, https://github.com/muxkin/balance-rxns
Project-URL: Repository, https://github.com/muxkin/balance-rxns
Project-URL: Issues, https://github.com/muxkin/balance-rxns/issues
Author-email: Muxkin <muxkin@foxmail.com>
License: MIT
License-File: LICENSE
Keywords: balancing,chemical equations,chemistry,pymatgen,reactions
Classifier: Development Status :: 3 - Alpha
Classifier: Intended Audience :: Education
Classifier: Intended Audience :: Science/Research
Classifier: License :: OSI Approved :: MIT License
Classifier: Programming Language :: Python :: 3
Classifier: Programming Language :: Python :: 3.9
Classifier: Programming Language :: Python :: 3.10
Classifier: Programming Language :: Python :: 3.11
Classifier: Programming Language :: Python :: 3.12
Classifier: Programming Language :: Python :: 3.13
Classifier: Topic :: Scientific/Engineering :: Chemistry
Requires-Python: >=3.9
Requires-Dist: pymatgen>=2024.1.0
Requires-Dist: sympy>=1.12.0
